coxdev/__init__.py
coxdev/_version.py
coxdev/base.py
coxdev/coxc.cpython-311-x86_64-linux-gnu.so
coxdev/info.py
coxdev/stratified.py
coxdev-0.1.4.dist-info/METADATA
coxdev-0.1.4.dist-info/WHEEL
coxdev-0.1.4.dist-info/top_level.txt
coxdev-0.1.4.dist-info/RECORD
