Metadata-Version: 2.4
Name: coxdev
Version: 0.1.4
Summary: Library for computing Cox deviance
Author-email: Jonathan Taylor <jonathan.taylor@stanford.edu>, Trevor Hastie <hastie@stanford.edu>, Balasubramanian Narasimhan <naras@stanford.edu>
Maintainer-email: Jonathan Taylor <jonathan.taylor@stanford.edu>
License: BSD-3-Clause
Classifier: Development Status :: 3 - Alpha
Classifier: Environment :: Console
Classifier: Intended Audience :: Science/Research
Classifier: Operating System :: OS Independent
Classifier: Programming Language :: Python
Classifier: Topic :: Scientific/Engineering
Requires-Python: >=3.9
Requires-Dist: numpy>=1.7.1
Requires-Dist: joblib
Requires-Dist: scipy
